[
  {
    "groupValue": "101",
    "totalRows": 20,
    "conPackM3": 0,
    "conProductoM3": 0,
    "pctConPackM3": 0,
    "pctConProductoM3": 0,
    "conGemini": 0
  },
  {
    "groupValue": "0",
    "totalRows": 3,
    "conPackM3": 0,
    "conProductoM3": 0,
    "pctConPackM3": 0,
    "pctConProductoM3": 0,
    "conGemini": 0
  },
  {
    "groupValue": "1",
    "totalRows": 2,
    "conPackM3": 0,
    "conProductoM3": 0,
    "pctConPackM3": 0,
    "pctConProductoM3": 0,
    "conGemini": 0
  },
  {
    "groupValue": "3",
    "totalRows": 2,
    "conPackM3": 0,
    "conProductoM3": 0,
    "pctConPackM3": 0,
    "pctConProductoM3": 0,
    "conGemini": 0
  }
]