[
  {
    "groupValue": "157",
    "totalRows": 4530,
    "conPackM3": 0,
    "conProductoM3": 4012,
    "pctConPackM3": 0,
    "pctConProductoM3": 88.56512141280352,
    "conGemini": 0
  },
  {
    "groupValue": "159",
    "totalRows": 1414,
    "conPackM3": 0,
    "conProductoM3": 52,
    "pctConPackM3": 0,
    "pctConProductoM3": 3.6775106082036775,
    "conGemini": 0
  },
  {
    "groupValue": "156",
    "totalRows": 1286,
    "conPackM3": 0,
    "conProductoM3": 1143,
    "pctConPackM3": 0,
    "pctConProductoM3": 88.88024883359253,
    "conGemini": 0
  },
  {
    "groupValue": "106",
    "totalRows": 1197,
    "conPackM3": 0,
    "conProductoM3": 774,
    "pctConPackM3": 0,
    "pctConProductoM3": 64.66165413533834,
    "conGemini": 0
  },
  {
    "groupValue": "102",
    "totalRows": 892,
    "conPackM3": 0,
    "conProductoM3": 865,
    "pctConPackM3": 0,
    "pctConProductoM3": 96.97309417040358,
    "conGemini": 0
  },
  {
    "groupValue": "111",
    "totalRows": 862,
    "conPackM3": 0,
    "conProductoM3": 381,
    "pctConPackM3": 0,
    "pctConProductoM3": 44.19953596287703,
    "conGemini": 0
  },
  {
    "groupValue": "154",
    "totalRows": 847,
    "conPackM3": 0,
    "conProductoM3": 235,
    "pctConPackM3": 0,
    "pctConProductoM3": 27.744982290436838,
    "conGemini": 0
  },
  {
    "groupValue": "152",
    "totalRows": 718,
    "conPackM3": 0,
    "conProductoM3": 696,
    "pctConPackM3": 0,
    "pctConProductoM3": 96.93593314763231,
    "conGemini": 0
  },
  {
    "groupValue": "153",
    "totalRows": 611,
    "conPackM3": 0,
    "conProductoM3": 431,
    "pctConPackM3": 0,
    "pctConProductoM3": 70.54009819967266,
    "conGemini": 0
  },
  {
    "groupValue": "107",
    "totalRows": 548,
    "conPackM3": 0,
    "conProductoM3": 355,
    "pctConPackM3": 0,
    "pctConProductoM3": 64.78102189781022,
    "conGemini": 0
  },
  {
    "groupValue": "155",
    "totalRows": 520,
    "conPackM3": 0,
    "conProductoM3": 9,
    "pctConPackM3": 0,
    "pctConProductoM3": 1.7307692307692308,
    "conGemini": 0
  },
  {
    "groupValue": "115",
    "totalRows": 497,
    "conPackM3": 0,
    "conProductoM3": 266,
    "pctConPackM3": 0,
    "pctConProductoM3": 53.52112676056338,
    "conGemini": 0
  },
  {
    "groupValue": "150",
    "totalRows": 360,
    "conPackM3": 0,
    "conProductoM3": 234,
    "pctConPackM3": 0,
    "pctConProductoM3": 65,
    "conGemini": 0
  },
  {
    "groupValue": "158",
    "totalRows": 302,
    "conPackM3": 0,
    "conProductoM3": 275,
    "pctConPackM3": 0,
    "pctConProductoM3": 91.05960264900662,
    "conGemini": 0
  },
  {
    "groupValue": "151",
    "totalRows": 194,
    "conPackM3": 0,
    "conProductoM3": 174,
    "pctConPackM3": 0,
    "pctConProductoM3": 89.69072164948454,
    "conGemini": 0
  },
  {
    "groupValue": "160",
    "totalRows": 122,
    "conPackM3": 0,
    "conProductoM3": 94,
    "pctConPackM3": 0,
    "pctConProductoM3": 77.04918032786885,
    "conGemini": 0
  },
  {
    "groupValue": "101",
    "totalRows": 73,
    "conPackM3": 0,
    "conProductoM3": 48,
    "pctConPackM3": 0,
    "pctConProductoM3": 65.75342465753424,
    "conGemini": 0
  },
  {
    "groupValue": "113",
    "totalRows": 70,
    "conPackM3": 0,
    "conProductoM3": 19,
    "pctConPackM3": 0,
    "pctConProductoM3": 27.142857142857142,
    "conGemini": 0
  },
  {
    "groupValue": "0",
    "totalRows": 3,
    "conPackM3": 0,
    "conProductoM3": 3,
    "pctConPackM3": 0,
    "pctConProductoM3": 100,
    "conGemini": 0
  },
  {
    "groupValue": "1",
    "totalRows": 2,
    "conPackM3": 0,
    "conProductoM3": 0,
    "pctConPackM3": 0,
    "pctConProductoM3": 0,
    "conGemini": 0
  },
  {
    "groupValue": "3",
    "totalRows": 2,
    "conPackM3": 0,
    "conProductoM3": 1,
    "pctConPackM3": 0,
    "pctConProductoM3": 50,
    "conGemini": 0
  }
]